{
    "id": "7c0c16f7015e52564dc38d376f033cb6",
    "name": "PRESCRIPTION_SURF",
    "title": "PRESCRIPTION_SURF",
    "description": "Table contenant les prescriptions surfaciques se superposant au document d'urbanisme et le lien avec le texte qui la décrit",
    "columns": [
        {
            "type": "String",
            "id": "01027e45ef26f92573baa6acbe0c642a",
            "name": "NATURE",
            "title": "NATURE",
            "description": "NATURE",
            "constraints": {
                "required": false,
                "unique": false,
                "maxLength": 50
            }
        },
        {
            "type": "MultiPolygon",
            "id": "0897733e595ddac8ee9cf24e7206eee6",
            "name": "WKT",
            "title": "Géométrie",
            "description": "Géométrie associée",
            "constraints": {
                "required": true,
                "unique": true
            }
        },
        {
            "type": "Filename",
            "id": "1e5ad3ce20264bcf57bbef2db38c606f",
            "name": "NOMFIC",
            "title": "NOMFIC",
            "description": "Nom du fichier PDF décrivant la prescription",
            "constraints": {
                "required": false,
                "unique": false,
                "maxLength": 80
            }
        },
        {
            "type": "String",
            "id": "364196a669d12c1984b8b156874b56f6",
            "name": "DATVALID",
            "title": "DATVALID",
            "description": "Date de la dernière validation de la prescription",
            "constraints": {
                "required": false,
                "unique": false,
                "pattern": "[0-9]{8}"
            }
        },
        {
            "type": "String",
            "id": "3fdf1e012d34a47ad657bf91efd2ff18",
            "name": "LIBELLE",
            "title": "LIBELLE",
            "description": "Intitulé complet de la prescription",
            "constraints": {
                "required": true,
                "unique": false,
                "maxLength": 254
            }
        },
        {
            "type": "String",
            "id": "4a0bb8e59d1644b5b1158e6c42e6a36e",
            "name": "TYPEPSC",
            "title": "TYPEPSC",
            "description": "Type de la prescription dans une liste prédéfinie",
            "constraints": {
                "required": true,
                "unique": false,
                "enum": [
                    "01",
                    "02",
                    "03",
                    "04",
                    "05",
                    "07",
                    "08",
                    "13",
                    "14",
                    "15",
                    "16",
                    "17",
                    "18",
                    "19",
                    "20",
                    "22",
                    "23",
                    "24",
                    "25",
                    "26",
                    "27",
                    "28",
                    "29",
                    "30",
                    "31",
                    "32",
                    "33",
                    "34",
                    "35",
                    "36",
                    "37",
                    "38",
                    "39",
                    "40",
                    "41",
                    "42",
                    "43",
                    "44",
                    "45",
                    "46",
                    "47",
                    "48",
                    "49",
                    "50",
                    "51",
                    "52",
                    "97",
                    "99"
                ],
                "maxLength": 2
            }
        },
        {
            "type": "String",
            "id": "69210d54f9cc444fc48a01efb457e7c1",
            "name": "LIB_IDPSC",
            "title": "LIB_IDPSC",
            "description": "identifiant d'objets",
            "constraints": {
                "required": false,
                "presenceRequired": false,
                "unique": false,
                "pattern": "[0-9]{9}_PLUI_[0-9]{8}_PS[0-9]+",
                "maxLength": 40
            }
        },
        {
            "type": "String",
            "id": "869137c7ad747093a14142e12bc51f69",
            "name": "TXT",
            "title": "TXT",
            "description": "Nom court de la prescription servant à faire une étiquette",
            "constraints": {
                "required": false,
                "unique": false,
                "maxLength": 10
            }
        },
        {
            "type": "String",
            "id": "a9c284e49e868f5b55ae31261333ff3e",
            "name": "IDURBA",
            "title": "IDURBA",
            "description": "Identifiant du document d'urbanisme",
            "constraints": {
                "required": true,
                "unique": false,
                "maxLength": 30
            }
        },
        {
            "type": "String",
            "id": "b3ae8e79b82db9812b225f87f42df7d0",
            "name": "SYMBOLE",
            "title": "SYMBOLE",
            "description": "SYMBOLE",
            "constraints": {
                "required": false,
                "unique": false,
                "pattern": "PSC-S_[0-9]{2}-[0-9]{2}_[0-9]{3}",
                "maxLength": 20
            }
        },
        {
            "type": "Url",
            "id": "be5fdce822b49d8740bbc90397a0e3e3",
            "name": "URLFIC",
            "title": "URLFIC",
            "description": "URL ou URI qui pointe sur le fichier de règlement de la prescription",
            "constraints": {
                "required": false,
                "unique": false,
                "maxLength": 254
            }
        },
        {
            "type": "String",
            "id": "d03ec530da11767aee450377e506524b",
            "name": "STYPEPSC",
            "title": "STYPEPSC",
            "constraints": {
                "required": true,
                "unique": false,
                "enum": [
                    "00",
                    "01",
                    "02",
                    "03",
                    "04",
                    "05",
                    "06",
                    "07",
                    "08",
                    "09",
                    "10",
                    "11",
                    "12",
                    "13",
                    "14",
                    "97",
                    "98"
                ],
                "maxLength": 2
            }
        }
    ],
    "constraints": {
        "conditions": [
            "TYPEPSC NOT LIKE '97' OR STYPEPSC NOT LIKE '00' OR NOMFIC IS NOT NULL"
        ],
        "foreignKeys": [
            "(TYPEPSC, STYPEPSC) REFERENCES PrescriptionUrbaType(TYPEPSC, STYPEPSC)"
        ]
    }
}