<?xml version="1.0" encoding="UTF-8"?>
<document>
  <id><![CDATA[34ac41b6d62e11e9bb652a2ae2dbcce4]]></id>
  <name><![CDATA[cnig_SCoT_2013]]></name>
  <description><![CDATA[maillage_SCoT_datappro(_part)]]></description>
  <regexp><![CDATA[[0-9]{9}_SCOT]]></regexp>
  <files>
    <file>
      <id><![CDATA[d202a4cf49183a7d705ddc0e5c9b4559]]></id>
      <name><![CDATA[SCOT]]></name>
      <path><![CDATA[SCOT]]></path>
      <type><![CDATA[table]]></type>
      <mandatory><![CDATA[OPTIONAL]]></mandatory>
    </file>
    <file>
      <id><![CDATA[8a315610d2b0f482f8dfb8c5d532de6e]]></id>
      <name><![CDATA[DOO]]></name>
      <path><![CDATA[[0-9]{9}_doo_[0-9]{8}]]></path>
      <type><![CDATA[pdf]]></type>
      <mandatory><![CDATA[WARN]]></mandatory>
    </file>
    <file>
      <id><![CDATA[9f29e5d6dc283479ee2a282ff283ed90]]></id>
      <name><![CDATA[PADD]]></name>
      <path><![CDATA[[0-9]{9}_padd_[0-9]{8}]]></path>
      <type><![CDATA[pdf]]></type>
      <mandatory><![CDATA[WARN]]></mandatory>
    </file>
    <file>
      <id><![CDATA[6376c47acf5938873936806f05e5df1b]]></id>
      <name><![CDATA[RAPPORT]]></name>
      <path><![CDATA[[0-9]{9}_rapport_[0-9]{8}]]></path>
      <type><![CDATA[pdf]]></type>
      <mandatory><![CDATA[WARN]]></mandatory>
    </file>
  </files>
</document>
